{
  "iconDefinitions": {
    "_file": {
      "iconPath": "icons/file.png"
    },
    "_folder": {
      "iconPath": "icons/folder.png"
    },
    "_folder-open": {
      "iconPath": "icons/folder-open.png"
    },
    "_css": {
      "iconPath": "icons/css.png"
    },
    "_html": {
      "iconPath": "icons/html.png"
    },
    "_javascript": {
      "iconPath": "icons/javascript.png"
    },
    "_java": {
      "iconPath": "icons/java.png"
    },
    "_kotlin": {
      "iconPath": "icons/kotlin.png"
    },
    "_git": {
      "iconPath": "icons/frc.png"
    },
    "_frc": {
      "iconPath": "icons/frc.png"
    },
    "_wmlog": {
      "iconPath": "icons/wmlog.png"
    },
    "_robotcontainer": {
      "iconPath": "icons/box.png"
    },
    "_robot": {
      "iconPath": "icons/box-locked.png"
    },
    "_constants": {
      "iconPath": "icons/constants.png"
    },
    "_swerve": {
      "iconPath": "icons/engine.png"
    },
    "_swerve-open": {
      "iconPath": "icons/engine-open.png"
    },
    "_global": {
      "iconPath": "icons/globe.png"
    },
    "_image": {
      "iconPath": "icons/image.png"
    },
    "_readme": {
      "iconPath": "icons/book.png"
    },
    "_pathplanner": {
      "iconPath": "icons/pathplanner.png"
    },
    "_pathplanner-open": {
      "iconPath": "icons/pathplanner-open.png"
    },
    "_path": {
      "iconPath": "icons/path.png"
    },
    "_folder_locked": {
      "iconPath": "icons/folder-locked.png"
    },
    "_folder_locked-open": {
      "iconPath": "icons/folder-locked-open.png"
    },
    "_continuity": {
      "iconPath": "icons/cont.png"
    },
    "_continuity-open": {
      "iconPath": "icons/cont-open.png"
    },
    "_main": {
      "iconPath": "icons/box-x.png"
    },
    "_led": {
      "iconPath": "icons/led.png"
    },
    "_led-open": {
      "iconPath": "icons/led-open.png"
    },
    "_wmlib": {
      "iconPath": "icons/wmlib.png"
    },
    "_wmlib-open": {
      "iconPath": "icons/wmlib-open.png"
    },
    "_wmlib_extras": {
      "iconPath": "icons/wmlib_extras.png"
    },
    "_wmlib_extras-open": {
      "iconPath": "icons/wmlib_extras-open.png"
    },
    "_util": {
      "iconPath": "icons/util.png"
    },
    "_util-open": {
      "iconPath": "icons/util-open.png"
    },
    "_wmlib_logs": {
      "iconPath": "icons/wmlib_logs.png"
    },
    "_wmlib_logs-open": {
      "iconPath": "icons/wmlib_logs-open.png"
    },
    "_vendordeps": {
      "iconPath": "icons/vendors.png"
    },
    "_vendordeps-open": {
      "iconPath": "icons/vendors-open.png"
    },
    "_subsystem_file": {
      "iconPath": "icons/subsystem.png"
    },
    "_wpilib": {
      "iconPath": "icons/wpilib.png"
    }
  
  },
  "file": "_file",
  "folder": "_folder",
  "folderExpanded": "_folder-open",
  "fileExtensions": {
    "kt": "_kotlin",  
    "java": "_java", 
    "html": "_html",  
    "css": "_css",    
    "js": "_javascript", 
    "git": "_git",
    "png": "_image",
    "jpg": "_image",   
    "svg": "_image",   
    "webp": "_image",
    "ico": "_image",
    "md": "_readme",
    "path": "_path",
    "wmlog": "_wmlog"
  },
  "fileNames": {
    "Constants.kt": "_constants",
    "RobotContainer.kt": "_robotcontainer",
    "Robot.kt": "_robot",
    "Main.kt": "_main",

    "Constants.java": "_constants",
    "RobotContainer.java": "_robotcontainer",
    "Robot.java": "_robot",
    "Main.java": "_main",

    ".gitignore": "_readme",

    "DriveSubsystem.kt": "_subsystem_file",
    "SwerveSubsystem.kt": "_subsystem_file",
    "Subsystem.kt": "_subsystem_file",
    "GrabberSubsystem.kt": "_subsystem_file",
    "ClawSubsystem.kt": "_subsystem_file",
    "ElevatorSubsystem.kt": "_subsystem_file",
    "IntakeSubsystem.kt": "_subsystem_file",
    "IndexerSubsystem.kt": "_subsystem_file",
    "ShooterSubsystem.kt": "_subsystem_file",
    "VisionSubsystem.kt": "_subsystem_file",
    "PhotonSubsystem.kt": "_subsystem_file",

    "DriveSubsystem.java": "_subsystem_file",
    "SwerveSubsystem.java": "_subsystem_file",
    "Subsystem.java": "_subsystem_file",
    "GrabberSubsystem.java": "_subsystem_file",
    "ClawSubsystem.java": "_subsystem_file",
    "ElevatorSubsystem.java": "_subsystem_file",
    "IntakeSubsystem.java": "_subsystem_file",
    "IndexerSubsystem.java": "_subsystem_file",
    "ShooterSubsystem.java": "_subsystem_file",
    "VisionSubsystem.java": "_subsystem_file",
    "PhotonSubsystem.java": "_subsystem_file",

    "SUB_Drive.java": "_subsystem_file",
    "SUB_Swerve.java": "_subsystem_file",
    "SUB_Grabber.java": "_subsystem_file",
    "SUB_Claw.java": "_subsystem_file",
    "SUB_Elevator.java": "_subsystem_file",
    "SUB_Intake.java": "_subsystem_file",
    "SUB_Indexer.java": "_subsystem_file",
    "SUB_Conveyor.java": "_subsystem_file",
    "SUB_Vision.java": "_subsystem_file",
    "SUB_Photon.java": "_subsystem_file"

  },
  "languageIds": {
    "java": "_java",
    "javascript": "_javascript",
    "css": "_css",
    "html": "_html",
    "json": "_json",
    "git": "_readme"
  },
  "folderNames":{
    "swerve": "_swerve",
    "pathplanner": "_pathplanner",
    "deploy": "_folder_locked",
    "continuity": "_continuity",
    "led": "_led",
    "wmlib": "_wmlib",
    "wmlib_extras": "_wmlib_extras",
    "util": "_util",
    "wmlib_logs": "_wmlib_logs",
    "vendordeps": "_vendordeps",
    "src": "_frc",
    "main": "_frc",
    ".wpilib": "_wpilib",
    ".pathplanner": "_pathplanner"
  },
  "folderNamesExpanded":{
    "swerve": "_swerve-open",
    "pathplanner": "_pathplanner-open",
    "deploy": "_folder_locked-open",
    "continuity": "_continuity-open",
    "led": "_led-open",
    "wmlib": "_wmlib-open",
    "wmlib_extras": "_wmlib_extras-open",
    "util": "_util-open",
    "wmlib_logs": "_wmlib_logs-open",
    "vendordeps": "_vendordeps-open",
    "src": "_frc",
    "main": "_frc",
    ".wpilib": "_wpilib",
    ".pathplanner": "_pathplanner"
  }
}
